huace_aigc_frame/__init__.py
huace_aigc_frame/logger.py
huace_aigc_frame/oss_util.py
huace_aigc_frame-0.1.1.dist-info/licenses/LICENSE
huace_aigc_frame-0.1.1.dist-info/METADATA
huace_aigc_frame-0.1.1.dist-info/WHEEL
huace_aigc_frame-0.1.1.dist-info/top_level.txt
huace_aigc_frame-0.1.1.dist-info/RECORD
