Metadata-Version: 2.4
Name: huace-aigc-frame
Version: 0.1.1
Summary: 华策AIGC框架 - 阿里云OSS工具包
Author-email: Huace <support@huace.com>
License: MIT
Project-URL: Homepage, https://github.com/huace/huace-aigc-frame
Project-URL: Repository, https://github.com/huace/huace-aigc-frame
Keywords: oss,aliyun,aigc,huace
Classifier: Development Status :: 4 - Beta
Classifier: Intended Audience :: Developers
Classifier: License :: OSI Approved :: MIT License
Classifier: Programming Language :: Python :: 3
Classifier: Programming Language :: Python :: 3.7
Classifier: Programming Language :: Python :: 3.8
Classifier: Programming Language :: Python :: 3.9
Classifier: Programming Language :: Python :: 3.10
Classifier: Programming Language :: Python :: 3.11
Classifier: Programming Language :: Python :: 3.12
Requires-Python: >=3.7
License-File: LICENSE
Requires-Dist: oss2>=2.17.0
Dynamic: license-file
